odoo/addons/shopinvader_api_lead/README.rst
odoo/addons/shopinvader_api_lead/__init__.py
odoo/addons/shopinvader_api_lead/__manifest__.py
odoo/addons/shopinvader_api_lead/i18n/shopinvader_api_lead.pot
odoo/addons/shopinvader_api_lead/readme/CONTRIBUTORS.rst
odoo/addons/shopinvader_api_lead/readme/DESCRIPTION.rst
odoo/addons/shopinvader_api_lead/routers/__init__.py
odoo/addons/shopinvader_api_lead/routers/lead.py
odoo/addons/shopinvader_api_lead/schemas/__init__.py
odoo/addons/shopinvader_api_lead/schemas/lead.py
odoo/addons/shopinvader_api_lead/security/acl_crm_lead.xml
odoo/addons/shopinvader_api_lead/security/groups.xml
odoo/addons/shopinvader_api_lead/static/description/index.html
odoo/addons/shopinvader_api_lead/tests/__init__.py
odoo/addons/shopinvader_api_lead/tests/test_post_lead.py
odoo_addon_shopinvader_api_lead-16.0.1.0.1.dist-info/METADATA
odoo_addon_shopinvader_api_lead-16.0.1.0.1.dist-info/WHEEL
odoo_addon_shopinvader_api_lead-16.0.1.0.1.dist-info/top_level.txt
odoo_addon_shopinvader_api_lead-16.0.1.0.1.dist-info/RECORD
